lightning_template/__init__.py
lightning_template/version.py
lightning_template/datasets/__init__.py
lightning_template/datasets/base.py
lightning_template/models/__init__.py
lightning_template/models/base.py
lightning_template/tools/__init__.py
lightning_template/tools/cli.py
lightning_template/tools/model/__init__.py
lightning_template/tools/model/batch_size_finder.py
lightning_template/tools/model/lr_finder.py
lightning_template/tools/model/model_statistics.py
lightning_template/utils/__init__.py
lightning_template/utils/callbacks/__init__.py
lightning_template/utils/callbacks/custom_repr.py
lightning_template/utils/callbacks/model_checkpoint.py
lightning_template/utils/callbacks/save_and_log_config_callback.py
lightning_template/utils/callbacks/set_precision_and_cudnn_callback.py
lightning_template/utils/callbacks/set_rich_traceback_handler.py
lightning_template/utils/callbacks/set_sharing_strategy_callback.py
lightning_template/utils/callbacks/set_wandb_logger_callback.py
lightning_template/utils/cli/__init__.py
lightning_template/utils/cli/cli.py
lightning_template/utils/cli/instantiate_class.py
lightning_template/utils/cli/trainer.py
lightning_template/utils/cli/argument_parsers/__init__.py
lightning_template/utils/cli/argument_parsers/deep_update.py
lightning_template/utils/cli/argument_parsers/json_file_action.py
lightning_template/utils/cli/argument_parsers/yaml_with_merge.py
lightning_template/utils/loggers/__init__.py
lightning_template/utils/loggers/wandb.py
lightning_template/utils/loop/__init__.py
lightning_template/utils/loop/kfold.py
lightning_template/utils/mixin/__init__.py
lightning_template/utils/mixin/split_name_mixin.py
lightning_template/utils/optim/__init__.py
lightning_template/utils/optim/configure_optimizers.py
lightning_template/utils/optim/keep_and_linearly_decay_lr_scheduler.py
lightning_template/utils/optim/warmup_lr_scheduler.py
lightning_template/utils/progress/__init__.py
lightning_template/utils/progress/rich_progress.py
lightning_template-1.12.4.dist-info/licenses/LICENSE
lightning_template-1.12.4.dist-info/METADATA
lightning_template-1.12.4.dist-info/WHEEL
lightning_template-1.12.4.dist-info/entry_points.txt
lightning_template-1.12.4.dist-info/top_level.txt
lightning_template-1.12.4.dist-info/RECORD
