Metadata-Version: 2.4
Name: lightning-template
Version: 1.12.4
Summary: A template wrapper for pytorch-lightning.
Author-email: shenmishajing <shenmishajing@gmail.com>
License: MIT License
Project-URL: Homepage, https://github.com/shenmishajing/lightning_template
Project-URL: Repository, https://github.com/shenmishajing/lightning_template
Project-URL: Documentation, https://lightning-template.readthedocs.io
Project-URL: Issues, https://github.com/shenmishajing/lightning_template/issues
Project-URL: Changelog, https://github.com/shenmishajing/lightning_template/blob/main/docs/get_started/changelog.md
Classifier: Development Status :: 5 - Production/Stable
Classifier: Intended Audience :: Developers
Classifier: License :: OSI Approved :: MIT License
Classifier: Operating System :: OS Independent
Classifier: Environment :: GPU :: NVIDIA CUDA
Classifier: Programming Language :: Python
Classifier: Programming Language :: Python :: 3
Classifier: Programming Language :: Python :: 3.8
Classifier: Programming Language :: Python :: 3.9
Classifier: Programming Language :: Python :: 3.10
Classifier: Programming Language :: Python :: 3.11
Classifier: Programming Language :: Python :: Implementation :: CPython
Classifier: Programming Language :: Python :: Implementation :: PyPy
Classifier: Topic :: Software Development :: Libraries
Classifier: Topic :: Software Development :: Libraries :: Python Modules
Classifier: Natural Language :: English
Requires-Python: <3.13,>=3.8
License-File: LICENSE
Requires-Dist: lightning>=2.0.0
Requires-Dist: jsonargparse[argcomplete,fsspec,ruyaml,signatures,urls]
Requires-Dist: scikit-learn
Provides-Extra: optional
Requires-Dist: wandb; extra == "optional"
Requires-Dist: rich; extra == "optional"
Requires-Dist: thop; extra == "optional"
Provides-Extra: deps
Requires-Dist: lightning-template[optional]; extra == "deps"
Provides-Extra: dev-commit
Requires-Dist: pre-commit; extra == "dev-commit"
Requires-Dist: commitizen; extra == "dev-commit"
Provides-Extra: dev-doc
Requires-Dist: sphinx; extra == "dev-doc"
Requires-Dist: sphinx-autobuild; extra == "dev-doc"
Requires-Dist: sphinx-book-theme; extra == "dev-doc"
Requires-Dist: sphinx-autoapi; extra == "dev-doc"
Requires-Dist: myst-parser; extra == "dev-doc"
Requires-Dist: sphinx_design; extra == "dev-doc"
Provides-Extra: dev-build
Requires-Dist: build; extra == "dev-build"
Provides-Extra: dev-test
Requires-Dist: tox; extra == "dev-test"
Requires-Dist: pytest; extra == "dev-test"
Requires-Dist: pytest-cov; extra == "dev-test"
Provides-Extra: dev-profile
Requires-Dist: torch_tb_profiler; extra == "dev-profile"
Provides-Extra: dev-core
Requires-Dist: lightning-template[dev-commit]; extra == "dev-core"
Provides-Extra: dev
Requires-Dist: lightning-template[dev-build,dev-core,dev-doc,dev-profile,dev-test]; extra == "dev"
Provides-Extra: all
Requires-Dist: lightning-template[deps,dev]; extra == "all"
Dynamic: license-file
